AUTHORS
LICENSE
MANIFEST.in
README.md
THANKS
setup.py
examples/example.json
gametex/__init__.py
gametex/admin.py
gametex/loader.py
gametex/models.py
gametex/management/__init__.py
gametex/management/commands/__init__.py
gametex/management/commands/load_gametex.py
gametex_django.egg-info/PKG-INFO
gametex_django.egg-info/SOURCES.txt
gametex_django.egg-info/dependency_links.txt
gametex_django.egg-info/requires.txt
gametex_django.egg-info/top_level.txt