Metadata-Version: 1.0
Name: gametex-django
Version: 0.3.5
Summary: Django integration for GameTeX
Home-page: http://github.com/ternus/gametex-django
Author: Christian Ternus
Author-email: ternus@cternus.net
License: Creative Commons Attribution-Noncommercial-Share Alike license
Platform: UNKNOWN
